SL-regression-quality/__init__.py
SL-regression-quality/code_example.py
SL-regression-quality/global_constants.py
SL-regression-quality/main_routine.py
SL-regression-quality/metrics.py
SL-regression-quality/outlier_detection.py
SL-regression-quality/parameters.py
SL-regression-quality/resolution.py
SL-regression-quality/user_messages.py
sl_regression_quality/__init__.py
sl_regression_quality/code_example.py
sl_regression_quality/global_constants.py
sl_regression_quality/load_data.py
sl_regression_quality/main_routine.py
sl_regression_quality/metrics.py
sl_regression_quality/outlier_detection.py
sl_regression_quality/parameters.py
sl_regression_quality/ram_consumption.py
sl_regression_quality/resolution.py
sl_regression_quality/test_code_example.py
sl_regression_quality/test_performance.py
sl_regression_quality/test_process.py
sl_regression_quality/user_messages.py
sl_regression_quality/vis_norma.py
sl_regression_quality/vis_outlier.py
sl_regression_quality/data/Data_x_y.csv
sl_regression_quality/data/Data_y_full.csv
sl_regression_quality/data/data_x_example.csv
sl_regression_quality/data/data_x_y_example.csv
sl_regression_quality/data/data_y_example.csv
sl_regression_quality-0.4.5.dist-info/LICENSE
sl_regression_quality-0.4.5.dist-info/METADATA
sl_regression_quality-0.4.5.dist-info/WHEEL
sl_regression_quality-0.4.5.dist-info/top_level.txt
sl_regression_quality-0.4.5.dist-info/RECORD
