Metadata-Version: 2.1
Name: sl-regression-quality
Version: 0.4.5
Summary: simple linear regression quality
Home-page: https://github.com/aplatag/project_SL_regression_quality.git
Author: EdelH, Aplata
License: MIT
License-File: LICENSE
Requires-Dist: numpy
Requires-Dist: pandas
Requires-Dist: statsmodels
Requires-Dist: scikit-learn
Requires-Dist: art
